qf_data/__init__.py
qf_data/align.py
qf_data/missing.py
qf_data/quality.py
qf_data/resample.py
qf_data/schema.py
qf_data/timeutils.py
qf_data/types.py
qf_data/adapters/pandas.py
qf_data/contrib/crypto_calendars.py
qf_data-0.1.0.dist-info/licenses/LICENSE
qf_data-0.1.0.dist-info/METADATA
qf_data-0.1.0.dist-info/WHEEL
qf_data-0.1.0.dist-info/top_level.txt
qf_data-0.1.0.dist-info/RECORD
