Metadata-Version: 2.4
Name: qf-data
Version: 0.1.0
Summary: Fast, minimal data utilities for trading: schemas, resampling, alignment, gaps, calendars.
Author-email: Your Name <you@example.com>
License: MIT
Keywords: trading,quant,data,resample,market data,crypto,finance
Classifier: Development Status :: 3 - Alpha
Classifier: Intended Audience :: Developers
Classifier: License :: OSI Approved :: MIT License
Classifier: Programming Language :: Python :: 3
Classifier: Programming Language :: Python :: 3 :: Only
Classifier: Programming Language :: Python :: 3.10
Classifier: Programming Language :: Python :: 3.11
Classifier: Programming Language :: Python :: 3.12
Classifier: Topic :: Office/Business :: Financial :: Investment
Requires-Python: >=3.10
License-File: LICENSE
Requires-Dist: numpy>=1.24
Requires-Dist: pyarrow>=15.0.0
Requires-Dist: python-dateutil>=2.8.2
Provides-Extra: pandas
Requires-Dist: pandas>=2.1; extra == "pandas"
Provides-Extra: test
Requires-Dist: pytest>=7.4; extra == "test"
Requires-Dist: hypothesis>=6.88; extra == "test"
Provides-Extra: dev
Requires-Dist: pytest>=7.4; extra == "dev"
Requires-Dist: hypothesis>=6.88; extra == "dev"
Requires-Dist: ruff>=0.6.9; extra == "dev"
Requires-Dist: mypy>=1.11; extra == "dev"
Dynamic: license-file
